src/control_unit.sv
`timescale 1ns / 1ps

// Single-cycle control unit
module control_unit (
  input wire [6:0] opcode,    // instruction opcode
  input wire [2:0] funct3,    // funct3 field
  input wire       funct7_5,  // top bit of funct7
  output reg       reg_write, // register file write enable
  output reg       alu_src,   // 0 = ALU second input from reg, 1 = immediate
  output reg       mem_read,  // data memory read enable
  output reg       mem_write, // data memory write enable
  output reg       mem_to_reg,// write-back source: 0 = ALU, 1 = memory
  output reg       branch,    // branch flag
  output reg [2:0] alu_op     // ALU operation code
);
  
  // ALU opcodes
  localparam ALU_ADD = 3'b000;
  localparam ALU_SUB = 3'b001;
  localparam ALU_AND = 3'b010;
  localparam ALU_OR  = 3'b011;
  localparam ALU_SLT = 3'b100;
  
  // RISC-V opcodes
  localparam OPC_RTYPE = 7'b0110011;  // R-type
  localparam OPC_LW    = 7'b0000011;  // Load word
  localparam OPC_SW    = 7'b0100011;  // Store word
  localparam OPC_BEQ   = 7'b1100011;  // Branch equal
  
  always @(*) begin
    // Default all signals to 0
    reg_write = 1'b0;
    alu_src = 1'b0;
    mem_read = 1'b0;
    mem_write = 1'b0;
    mem_to_reg = 1'b0;
    branch = 1'b0;
    alu_op = ALU_ADD;
    
    case(opcode)
      // R-type (ADD, SUB, AND, OR, SLT)
      OPC_RTYPE: begin
        reg_write = 1'b1;
        alu_src = 1'b0;      // use register data
        mem_to_reg = 1'b0;   // write ALU result to register
        case ({funct3, funct7_5})
          4'b0000: alu_op = ALU_ADD;  // ADD
          4'b0001: alu_op = ALU_SUB;  // SUB
          4'b1110: alu_op = ALU_AND;  // AND
          4'b1100: alu_op = ALU_OR;   // OR
          4'b0100: alu_op = ALU_SLT;  // SLT
          default: alu_op = ALU_ADD;
        endcase
      end
      
      // Load word
      OPC_LW: begin
        reg_write = 1'b1;    // write to register
        alu_src = 1'b1;      // use immediate for address calc
        mem_read = 1'b1;     // read from memory
        mem_to_reg = 1'b1;   // write memory data to register
        alu_op = ALU_ADD;    // address = base + offset
      end
      
      // Store word
      OPC_SW: begin
        alu_src = 1'b1;      // use immediate for address calc
        mem_write = 1'b1;    // write to memory
        alu_op = ALU_ADD;    // address = base + offset
      end
      
      // Branch equal
      OPC_BEQ: begin
        branch = 1'b1;       // enable branch logic
        alu_op = ALU_SUB;    // subtract to check equality
      end
      
      default: begin
        // Keep defaults (NOP behavior)
      end
    endcase
  end
endmodule

testbenches/control_unit_tb.sv
`timescale 1ns / 1ps

module control_unit_tb;
  // Inputs
  reg [6:0] opcode;
  reg [2:0] funct3;
  reg       funct7_5;
  // Outputs
  wire      reg_write;
  wire      alu_src;
  wire      mem_read;
  wire      mem_write;
  wire      mem_to_reg;
  wire      branch;
  wire [2:0] alu_op;

  // Instantiate the Control Unit
  control_unit uut (
    .opcode(opcode),
    .funct3(funct3),
    .funct7_5(funct7_5),
    .reg_write(reg_write),
    .alu_src(alu_src),
    .mem_read(mem_read),
    .mem_write(mem_write),
    .mem_to_reg(mem_to_reg),
    .branch(branch),
    .alu_op(alu_op)
  );

  initial begin
    // VCD generation
    $dumpfile("control_unit_tb.vcd");
    $dumpvars;
    
    $display("\nTime | opcode  funct3 funct7_5 | reg_wr alu_src mem_rd mem_wr mem2reg branch alu_op");
    $display("-------------------------------------------------------------------------------");

    // R-type: ADD
    opcode = 7'b0110011; funct3 = 3'b000; funct7_5 = 1'b0; #10;
    $display("ADD  | %b %b      %b   |   %b      %b      %b      %b      %b      %b     %b", opcode, funct3, funct7_5, reg_write, alu_src, mem_read, mem_write, mem_to_reg, branch, alu_op);

    // R-type: SUB
    opcode = 7'b0110011; funct3 = 3'b000; funct7_5 = 1'b1; #10;
    $display("SUB  | %b %b      %b   |   %b      %b      %b      %b      %b      %b     %b", opcode, funct3, funct7_5, reg_write, alu_src, mem_read, mem_write, mem_to_reg, branch, alu_op);

    // R-type: AND
    opcode = 7'b0110011; funct3 = 3'b111; funct7_5 = 1'b0; #10;
    $display("AND  | %b %b      %b   |   %b      %b      %b      %b      %b      %b     %b", opcode, funct3, funct7_5, reg_write, alu_src, mem_read, mem_write, mem_to_reg, branch, alu_op);

    // R-type: OR
    opcode = 7'b0110011; funct3 = 3'b110; funct7_5 = 1'b0; #10;
    $display("OR   | %b %b      %b   |   %b      %b      %b      %b      %b      %b     %b", opcode, funct3, funct7_5, reg_write, alu_src, mem_read, mem_write, mem_to_reg, branch, alu_op);

    // R-type: SLT
    opcode = 7'b0110011; funct3 = 3'b010; funct7_5 = 1'b0; #10;
    $display("SLT  | %b %b      %b   |   %b      %b      %b      %b      %b      %b     %b", opcode, funct3, funct7_5, reg_write, alu_src, mem_read, mem_write, mem_to_reg, branch, alu_op);

    // Load Word
    opcode = 7'b0000011; funct3 = 3'b010; funct7_5 = 1'b0; #10;
    $display("LW   | %b %b      %b   |   %b      %b      %b      %b      %b      %b     %b", opcode, funct3, funct7_5, reg_write, alu_src, mem_read, mem_write, mem_to_reg, branch, alu_op);

    // Store Word
    opcode = 7'b0100011; funct3 = 3'b010; funct7_5 = 1'b0; #10;
    $display("SW   | %b %b      %b   |   %b      %b      %b      %b      %b      %b     %b", opcode, funct3, funct7_5, reg_write, alu_src, mem_read, mem_write, mem_to_reg, branch, alu_op);

    // Branch if Equal
    opcode = 7'b1100011; funct3 = 3'b000; funct7_5 = 1'b0; #10;
    $display("BEQ  | %b %b      %b   |   %b      %b      %b      %b      %b      %b     %b", opcode, funct3, funct7_5, reg_write, alu_src, mem_read, mem_write, mem_to_reg, branch, alu_op);

    // Default (undefined opcode)
    opcode = 7'b1111111; funct3 = 3'bxxx; funct7_5 = 1'bx; #10;
    $display("DEF  | %b %b      %b   |   %b      %b      %b      %b      %b      %b     %b", opcode, funct3, funct7_5, reg_write, alu_src, mem_read, mem_write, mem_to_reg, branch, alu_op);

    $finish;
  end
endmodule

control_unit_tb.vcd
$date
   Tue Aug 26 02:29:21 2025
$end
$version
  2020.1
$end
$timescale
  1ps
$end
$scope module control_unit_tb $end
$var reg 7 ! opcode [6:0] $end
$var reg 3 " funct3 [2:0] $end
$var reg 1 # funct7_5 $end
$var wire 1 $ reg_write $end
$var wire 1 % alu_src $end
$var wire 1 & mem_read $end
$var wire 1 ' mem_write $end
$var wire 1 ( mem_to_reg $end
$var wire 1 ) branch $end
$var wire 3 * alu_op [2:0] $end
$scope module uut $end
$var wire 7 + opcode [6:0] $end
$var wire 3 , funct3 [2:0] $end
$var wire 1 - funct7_5 $end
$var reg 1 . reg_write $end
$var reg 1 / alu_src $end
$var reg 1 0 mem_read $end
$var reg 1 1 mem_write $end
$var reg 1 2 mem_to_reg $end
$var reg 1 3 branch $end
$var reg 3 4 alu_op [2:0] $end
$var parameter 3 5 ALU_ADD [2:0] $end
$var parameter 3 6 ALU_SUB [2:0] $end
$var parameter 3 7 ALU_AND [2:0] $end
$var parameter 3 8 ALU_OR [2:0] $end
$var parameter 3 9 ALU_SLT [2:0] $end
$var parameter 7 : OPC_RTYPE [6:0] $end
$var parameter 7 ; OPC_LW [6:0] $end
$var parameter 7 < OPC_SW [6:0] $end
$var parameter 7 = OPC_BEQ [6:0] $end
$upscope $end
$upscope $end
$enddefinitions $end
#0
$dumpvars
b110011 !
b0 "
0#
1$
0%
0&
0'
0(
0)
b0 *
b110011 +
b0 ,
0-
1.
0/
00
01
02
03
b0 4
b0 5
b1 6
b10 7
b11 8
b100 9
b110011 :
b11 ;
b100011 <
b1100011 =
$end
#10000
b110011 !
b0 "
1#
1$
b1 *
1-
1.
0/
00
01
02
03
b1 4
#20000
b110011 !
b111 "
0#
1$
b10 *
b111 ,
0-
1.
0/
00
01
02
03
b10 4
#30000
b110011 !
b110 "
1$
b11 *
b110 ,
1.
0/
00
01
02
03
b11 4
#40000
b110011 !
b10 "
1$
b100 *
b10 ,
1.
0/
00
01
02
03
b100 4
#50000
b11 !
b10 "
1$
1%
1&
1(
b0 *
b11 +
1.
1/
10
01
12
03
b0 4
#60000
b100011 !
b10 "
0$
1%
0&
1'
0(
b100011 +
0.
1/
00
11
02
03
b0 4
#70000
b1100011 !
b0 "
0%
0'
1)
b1 *
b1100011 +
b0 ,
0.
0/
00
01
02
13
b1 4
#80000
b1111111 !
bx "
x#
0)
b0 *
b1111111 +
bx ,
x-
0.
0/
00
01
02
03
b0 4
