src/data_memory.sv
`timescale 1ns / 1ps

// Single-cycle data memory for word-addressable loads and stores
module data_memory (
  input  wire        clk,        // clock for synchronous writes
  input  wire        mem_read,   // high to enable read
  input  wire        mem_write,  // high to enable write
  input  wire [31:0] addr,       // byte address
  input  wire [31:0] write_data, // data to write on store
  output wire [31:0] read_data   // data output on load
);

  // 256 × 32-bit memory array (1 KB)
  reg [31:0] mem [0:255];
  integer i;

  // Initialize memory to zero (optional)
  initial begin
    for (i = 0; i < 256; i = i + 1)
      mem[i] = 32'b0;
  end

  // Synchronous write
  always @(posedge clk) begin
    if (mem_write)
      mem[ addr[9:2] ] <= write_data;
  end

  // Asynchronous read (combinational)
  assign read_data = (mem_read) ? mem[ addr[9:2] ] : 32'b0;

endmodule

testbenches/data_memory_tb.sv
`timescale 1ns / 1ps

module data_memory_tb;
  // Testbench signals
  reg         clk;
  reg         mem_read;
  reg         mem_write;
  reg  [31:0] addr;
  reg  [31:0] write_data;
  wire [31:0] read_data;
  integer     i;

  // Instantiate the Data Memory
  data_memory uut (
    .clk(clk),
    .mem_read(mem_read),
    .mem_write(mem_write),
    .addr(addr),
    .write_data(write_data),
    .read_data(read_data)
  );

  // Clock generator: 10 ns period
  always #5 clk = ~clk;

  initial begin
    // Generate VCD file for waveform viewing (FIRST!)
    $dumpfile("data_memory_tb.vcd");
    $dumpvars;
    
    // Initialize
    clk         = 0;
    mem_read    = 0;
    mem_write   = 0;
    addr        = 0;
    write_data  = 0;

    // Initial read (should be zero)
    mem_read = 1; addr = 32'h0000_0000; #1;
    $display("Initial read at addr=0x%0h: read_data=0x%0h (expect 0)", addr, read_data);
    mem_read = 0; #9;

    // Write pattern to four words
    for (i = 0; i < 4; i = i + 1) begin
      addr       = i * 4;
      write_data = {28'd0, i};             // small value i
      mem_write  = 1; #10;                 // write on rising edge
      mem_write  = 0; #10;
      $display("Wrote 0x%0h at addr=0x%0h", write_data, addr);
    end

    // Read back the written values
    mem_read = 1;
    for (i = 0; i < 4; i = i + 1) begin
      addr = i * 4; #1;
      $display("Read  at addr=0x%0h: read_data=0x%0h", addr, read_data);
      #9;
    end
    mem_read = 0;

    // Read with mem_read=0 (should output zero)
    addr = 32'h0000_0000; #1;
    $display("Read with mem_read=0 at addr=0x%0h: read_data=0x%0h (expect 0)", addr, read_data);

    // Wait a bit and finish
    #10;
    $display("Simulation complete at time %0t", $time);
    $finish;
  end
endmodule

data_memory_tb.vcd
$date
   Mon Aug 25 01:28:37 2025
$end
$version
  2020.1
$end
$timescale
  1ps
$end
$scope module data_memory_tb $end
$var reg 1 ! clk $end
$var reg 1 " mem_read $end
$var reg 1 # mem_write $end
$var reg 32 $ addr [31:0] $end
$var reg 32 % write_data [31:0] $end
$var wire 32 & read_data [31:0] $end
$var integer 32 ' i $end
$scope module uut $end
$var wire 1 ( clk $end
$var wire 1 ) mem_read $end
$var wire 1 * mem_write $end
$var wire 32 + addr [31:0] $end
$var wire 32 , write_data [31:0] $end
$var wire 32 & read_data [31:0] $end
$var integer 32 - i $end
$upscope $end
$upscope $end
$enddefinitions $end
#0
$dumpvars
0!
1"
0#
b0 $
b0 %
b0 &
bx '
0(
1)
0*
b0 +
b0 ,
b100000000 -
$end
#1000
0"
b0 &
0)
#5000
1!
1(
#10000
0!
1#
b0 $
b0 %
b0 '
0(
1*
#15000
1!
1(
#20000
0!
0#
0(
0*
#25000
1!
1(
#30000
0!
1#
b100 $
b1 %
b0 &
b1 '
0(
1*
b100 +
b1 ,
#35000
1!
b0 &
1(
#40000
0!
0#
0(
0*
#45000
1!
1(
#50000
0!
1#
b1000 $
b10 %
b0 &
b10 '
0(
1*
b1000 +
b10 ,
#55000
1!
b0 &
1(
#60000
0!
0#
0(
0*
#65000
1!
1(
#70000
0!
1#
b1100 $
b11 %
b0 &
b11 '
0(
1*
b1100 +
b11 ,
#75000
1!
b0 &
1(
#80000
0!
0#
0(
0*
#85000
1!
1(
#90000
0!
1"
b0 $
b0 &
b0 '
0(
1)
b0 +
#95000
1!
1(
#100000
0!
b100 $
b1 &
b1 '
0(
b100 +
#105000
1!
1(
#110000
0!
b1000 $
b10 &
b10 '
0(
b1000 +
#115000
1!
1(
#120000
0!
b1100 $
b11 &
b11 '
0(
b1100 +
#125000
1!
1(
#130000
0!
0"
b0 $
b0 &
b100 '
0(
0)
b0 +
