src/instruction_memory.sv
`timescale 1ns / 1ps

module instruction_memory (
  input  wire [31:0] addr,        // PC address 
  output reg  [31:0] instruction  // 32-bit instruction
);
  
  // 256 × 32-bit instruction memory (1KB)
  reg [31:0] memory [0:255];
  
  initial begin
    // Initialize to NOPs
    integer i;
    for (i = 0; i < 256; i = i + 1) begin
      memory[i] = 32'h00000013;
    end
    
    // Load program from hex file if it exists
    // $readmemh("program.hex", memory);
  end
  
  // Combinational read - word-aligned addressing
  always @(*) begin
    instruction = memory[addr[9:2]];
  end
  
endmodule

testbenches/instruction_memory_tb.sv
`timescale 1ns / 1ps

module instruction_memory_tb;
  // signals
  reg  [31:0] pc;            // byte address input
  wire [31:0] instruction;   // instruction output
  integer i;                 // loop counter

  // instantiate DUT
  instruction_memory uut (
    .addr(pc),
    .instruction(instruction)
  );

  initial begin
    // VCD generation
    $dumpfile("instruction_memory_tb.vcd");
    $dumpvars;
    
    // preload the ROM
    uut.memory[0] = 32'hAA12B0C2;
    uut.memory[1] = 32'hAAC2B0C2;
    uut.memory[2] = 32'hAAD2B0C2;
    uut.memory[3] = 32'hA212B0C2;
    uut.memory[4] = 32'hA412B0C2;
    uut.memory[5] = 32'hA112B0C2;
    uut.memory[6] = 32'hA512B0C2;

    // step through seven instructions
    pc = 0;
    for (i = 0; i < 7; i = i + 1) begin
      #10;
      $display("%0t | pc=0x%0h | idx=0x%0h | instr=0x%0h",
               $time, pc, pc[9:2], instruction);
      pc = pc + 4;
    end

    $finish;
  end
endmodule

instruction_memory_tb.vcd
$date
   Tue Aug 26 02:17:23 2025
$end
$version
  2020.1
$end
$timescale
  1ps
$end
$scope module instruction_memory_tb $end
$var reg 32 ! pc [31:0] $end
$var wire 32 " instruction [31:0] $end
$var integer 32 # i $end
$scope module uut $end
$var wire 32 $ addr [31:0] $end
$var reg 32 % instruction [31:0] $end
$scope begin Block11_1 $end
$var integer 32 & i $end
$upscope $end
$upscope $end
$upscope $end
$enddefinitions $end
#0
$dumpvars
b0 !
b10101010000100101011000011000010 "
b0 #
b0 $
b10101010000100101011000011000010 %
b100000000 &
$end
#10000
b100 !
b10101010110000101011000011000010 "
b1 #
b100 $
b10101010110000101011000011000010 %
#20000
b1000 !
b10101010110100101011000011000010 "
b10 #
b1000 $
b10101010110100101011000011000010 %
#30000
b1100 !
b10100010000100101011000011000010 "
b11 #
b1100 $
b10100010000100101011000011000010 %
#40000
b10000 !
b10100100000100101011000011000010 "
b100 #
b10000 $
b10100100000100101011000011000010 %
#50000
b10100 !
b10100001000100101011000011000010 "
b101 #
b10100 $
b10100001000100101011000011000010 %
#60000
b11000 !
b10100101000100101011000011000010 "
b110 #
b11000 $
b10100101000100101011000011000010 %
#70000
b11100 !
b111 #
