src/pc.sv
`timescale 1ns / 1ps

module program_counter
  (input wire clk,
   input wire rst,
   input  wire [31:0] next_pc, 
   output reg [31:0] pc
  );
  
  always @(posedge clk or negedge rst)
    begin
      if (~rst)
        pc <= 32'b0;
      else if (pc >= 32'd1020) // Memory overflow protection
        pc <= 32'b0;
      else
        pc <= next_pc;
    end
endmodule

testbenches/pc_tb.sv
`timescale 1ns / 1ps

module program_counter_tb;
  // Signal declarations
  reg clk;
  reg rst;
  reg [31:0] next_pc; 
  wire [31:0] pc;
  
  // Instantiate program counter
  program_counter uut ( 
    .clk(clk), 
    .rst(rst), 
    .next_pc(next_pc),
    .pc(pc)
  );
  
  // Clock generation - 10MHz
  always #50 clk = ~clk;
  
  // Test stimulus
  initial begin
    // VCD dump for waveform analysis
    $dumpfile("pc_simulation.vcd");
    $dumpvars(0);
    
    clk = 0;
    rst = 0;
    next_pc = 32'h00000000;
    
    $display("=== PC Testbench Starting ===");
    
    // Hold reset for 2 clock cycles
    #200;
    rst = 1;
    $display("Reset released at time %0t", $time);
    
    // Test sequential execution
    $display("--- Testing Sequential Execution ---");
    repeat(20) begin
      #100;
      next_pc = next_pc + 4;
    end
    
    // Test jump to address 0x100
    $display("--- Testing Jump to address 0x100 ---");
    next_pc = 32'h00000100;
    #300;
    
    // Continue sequential from new address
    repeat(10) begin
      #100;
      next_pc = next_pc + 4;
    end
    
    // Test jump to address 0x200
    $display("--- Testing Jump to address 0x200 ---");
    next_pc = 32'h00000200;
    #300;
    
    // Test backward jump (loop simulation)
    $display("--- Testing Loop (backward jump) ---");
    next_pc = 32'h00000180;
    #300;
    repeat(5) begin
      #100;
      next_pc = next_pc + 4;
    end
    
    // Test overflow protection
    $display("--- Testing Overflow Protection ---");
    next_pc = 32'd1016;
    #300;
    next_pc = 32'd1020;
    #300;
    next_pc = 32'd1024;
    #300;
    
    // Test reset during operation
    $display("--- Testing Reset During Operation ---");
    rst = 0;
    #200;
    rst = 1;
    next_pc = 32'h00000008;
    #500;
    
    $display("=== PC Testbench Complete ===");
    $finish;
  end
  
  // Monitor signal changes
  initial begin 
    $monitor("Time %0t | clk %b | rst %b | next_pc %0d | pc %0d", 
             $time, clk, rst, next_pc, pc);
  end
endmodule

pc_simulation.vcd
$date
   Mon Aug 25 00:26:41 2025
$end
$version
  2020.1
$end
$timescale
  1ps
$end
$scope module program_counter_tb $end
$var reg 1 ! clk $end
$var reg 1 " rst $end
$var reg 32 # next_pc [31:0] $end
$var wire 32 $ pc [31:0] $end
$scope module uut $end
$var wire 1 % clk $end
$var wire 1 & rst $end
$var wire 32 ' next_pc [31:0] $end
$var reg 32 ( pc [31:0] $end
$upscope $end
$upscope $end
$enddefinitions $end
#0
$dumpvars
0!
0"
b0 #
b0 $
0%
0&
b0 '
b0 (
$end
#50000
1!
1%
b0 (
#100000
0!
0%
#150000
1!
1%
b0 (
#200000
0!
1"
0%
1&
#250000
1!
1%
b0 (
#300000
0!
b100 #
0%
b100 '
#350000
1!
b100 $
1%
b100 (
#400000
0!
b1000 #
0%
b1000 '
#450000
1!
b1000 $
1%
b1000 (
#500000
0!
b1100 #
0%
b1100 '
#550000
1!
b1100 $
1%
b1100 (
#600000
0!
b10000 #
0%
b10000 '
#650000
1!
b10000 $
1%
b10000 (
#700000
0!
b10100 #
0%
b10100 '
#750000
1!
b10100 $
1%
b10100 (
#800000
0!
b11000 #
0%
b11000 '
#850000
1!
b11000 $
1%
b11000 (
#900000
0!
b11100 #
0%
b11100 '
#950000
1!
b11100 $
1%
b11100 (
#1000000
0!
b100000 #
0%
b100000 '
#1050000
1!
b100000 $
1%
b100000 (
#1100000
0!
b100100 #
0%
b100100 '
#1150000
1!
b100100 $
1%
b100100 (
#1200000
0!
b101000 #
0%
b101000 '
#1250000
1!
b101000 $
1%
b101000 (
#1300000
0!
b101100 #
0%
b101100 '
#1350000
1!
b101100 $
1%
b101100 (
#1400000
0!
b110000 #
0%
b110000 '
#1450000
1!
b110000 $
1%
b110000 (
#1500000
0!
b110100 #
0%
b110100 '
#1550000
1!
b110100 $
1%
b110100 (
#1600000
0!
b111000 #
0%
b111000 '
#1650000
1!
b111000 $
1%
b111000 (
#1700000
0!
b111100 #
0%
b111100 '
#1750000
1!
b111100 $
1%
b111100 (
#1800000
0!
b1000000 #
0%
b1000000 '
#1850000
1!
b1000000 $
1%
b1000000 (
#1900000
0!
b1000100 #
0%
b1000100 '
#1950000
1!
b1000100 $
1%
b1000100 (
#2000000
0!
b1001000 #
0%
b1001000 '
#2050000
1!
b1001000 $
1%
b1001000 (
#2100000
0!
b1001100 #
0%
b1001100 '
#2150000
1!
b1001100 $
1%
b1001100 (
#2200000
0!
b100000000 #
0%
b100000000 '
#2250000
1!
b100000000 $
1%
b100000000 (
#2300000
0!
0%
#2350000
1!
1%
b100000000 (
#2400000
0!
0%
#2450000
1!
1%
b100000000 (
#2500000
0!
0%
#2550000
1!
1%
b100000000 (
#2600000
0!
b100000100 #
0%
b100000100 '
#2650000
1!
b100000100 $
1%
b100000100 (
#2700000
0!
b100001000 #
0%
b100001000 '
#2750000
1!
b100001000 $
1%
b100001000 (
#2800000
0!
b100001100 #
0%
b100001100 '
#2850000
1!
b100001100 $
1%
b100001100 (
#2900000
0!
b100010000 #
0%
b100010000 '
#2950000
1!
b100010000 $
1%
b100010000 (
#3000000
0!
b100010100 #
0%
b100010100 '
#3050000
1!
b100010100 $
1%
b100010100 (
#3100000
0!
b100011000 #
0%
b100011000 '
#3150000
1!
b100011000 $
1%
b100011000 (
#3200000
0!
b100011100 #
0%
b100011100 '
#3250000
1!
b100011100 $
1%
b100011100 (
#3300000
0!
b100100000 #
0%
b100100000 '
#3350000
1!
b100100000 $
1%
b100100000 (
#3400000
0!
b100100100 #
0%
b100100100 '
#3450000
1!
b100100100 $
1%
b100100100 (
#3500000
0!
b1000000000 #
0%
b1000000000 '
#3550000
1!
b1000000000 $
1%
b1000000000 (
#3600000
0!
0%
#3650000
1!
1%
b1000000000 (
#3700000
0!
0%
#3750000
1!
1%
b1000000000 (
#3800000
0!
b110000000 #
0%
b110000000 '
#3850000
1!
b110000000 $
1%
b110000000 (
#3900000
0!
0%
#3950000
1!
1%
b110000000 (
#4000000
0!
0%
#4050000
1!
1%
b110000000 (
#4100000
0!
0%
#4150000
1!
1%
b110000000 (
#4200000
0!
b110000100 #
0%
b110000100 '
#4250000
1!
b110000100 $
1%
b110000100 (
#4300000
0!
b110001000 #
0%
b110001000 '
#4350000
1!
b110001000 $
1%
b110001000 (
#4400000
0!
b110001100 #
0%
b110001100 '
#4450000
1!
b110001100 $
1%
b110001100 (
#4500000
0!
b110010000 #
0%
b110010000 '
#4550000
1!
b110010000 $
1%
b110010000 (
#4600000
0!
b1111111000 #
0%
b1111111000 '
#4650000
1!
b1111111000 $
1%
b1111111000 (
#4700000
0!
0%
#4750000
1!
1%
b1111111000 (
#4800000
0!
0%
#4850000
1!
1%
b1111111000 (
#4900000
0!
b1111111100 #
0%
b1111111100 '
#4950000
1!
b1111111100 $
1%
b1111111100 (
#5000000
0!
0%
#5050000
1!
b0 $
1%
b0 (
#5100000
0!
0%
#5150000
1!
b1111111100 $
1%
b1111111100 (
#5200000
0!
b10000000000 #
0%
b10000000000 '
#5250000
1!
b0 $
1%
b0 (
#5300000
0!
0%
#5350000
1!
b10000000000 $
1%
b10000000000 (
#5400000
0!
0%
#5450000
1!
b0 $
1%
b0 (
#5500000
0!
0"
0%
0&
b0 (
#5550000
1!
1%
b0 (
#5600000
0!
0%
#5650000
1!
1%
b0 (
#5700000
0!
1"
b1000 #
0%
1&
b1000 '
#5750000
1!
b1000 $
1%
b1000 (
#5800000
0!
0%
#5850000
1!
1%
b1000 (
#5900000
0!
0%
#5950000
1!
1%
b1000 (
#6000000
0!
0%
#6050000
1!
1%
b1000 (
#6100000
0!
0%
#6150000
1!
1%
b1000 (
