src/register_file.sv
`timescale 1ns / 1ps

module register_file (
  input  wire        clk,
  input  wire        we,
  input  wire [4:0]  rd,
  input  wire [31:0] wd,
  input  wire [4:0]  rs1,
  input  wire [4:0]  rs2,
  output wire [31:0] rd1,
  output wire [31:0] rd2
);

  // 32 × 32-bit register array
  reg [31:0] regs [0:31];
  integer i;

  // Initialize all registers to zero at time 0
  initial begin
    for (i = 0; i < 32; i = i + 1) begin
      regs[i] = 32'b0;
    end
  end

  // Synchronous write on rising clock edge
  always @(posedge clk) begin
    if (we && rd != 5'd0) begin
      regs[rd] <= wd;
    end
  end

  // Asynchronous reads; x0 is always zero
  assign rd1 = (rs1 == 5'd0) ? 32'b0 : regs[rs1];
  assign rd2 = (rs2 == 5'd0) ? 32'b0 : regs[rs2];

endmodule

testbenches/register_file_tb.sv
`timescale 1ns / 1ps

module register_file_tb;
  // Testbench signals
  reg         clk;
  reg         we;
  reg  [4:0]  rd, rs1, rs2;
  reg  [31:0] wd;
  wire [31:0] rd1, rd2;
  integer     i;

  // Instantiate register file
  register_file uut (
    .clk(clk),
    .we(we),
    .rd(rd),
    .wd(wd),
    .rs1(rs1),
    .rs2(rs2),
    .rd1(rd1),
    .rd2(rd2)
  );

  // Clock generator: 10 ns period
  always #5 clk = ~clk;

  initial begin
    // Generate VCD file for waveform viewing
    $dumpfile("register_file_tb.vcd");
    $dumpvars;
    
    // Initialize
    clk   = 0;
    we    = 0;
    rd    = 0;
    rs1   = 0;
    rs2   = 0;
    wd    = 0;

    // Wait a couple cycles and check reset state (all zeros)
    #20;
    $display("Initial: rd1=0x%0h rd2=0x%0h (should both be 0)", rd1, rd2);

    // Write 0xDEADBEEF to x1
    we  = 1;
    rd  = 5'd1;
    wd  = 32'hDEADBEEF;
    rs1 = 5'd1;  rs2 = 5'd0;
    #10;         // on posedge clk
    we  = 0;
    #10;
    $display("After write x1: rd1=0x%0h (expect DEADBEEF), rd2=0x%0h (expect 0)", rd1, rd2);

    // Attempt write to x0 (should be ignored)
    we  = 1;
    rd  = 5'd0;
    wd  = 32'hCAFEBABE;
    rs1 = 5'd0;
    #10;
    we  = 0;
    #10;
    $display("After write x0: rd1=0x%0h (still 0)", rd1);

    // Write distinct values to x2 and x3 and read both
    for (i = 2; i <= 3; i = i + 1) begin
      we  = 1;
      rd  = i;
      wd  = {i[3:0], i[3:0], i[3:0], i[3:0]};
      rs1 = i;
      rs2 = (i==2) ? 5'd3 : 5'd2;
      #10;
      we  = 0;
      #10;
      $display("Write x%0d=0x%0h -> rd1=0x%0h rd2=0x%0h",
               i, wd, rd1, rd2);
    end

    // Wait a bit more and finish
    #10;
    $display("Simulation complete at time %0t", $time);
    $finish;
  end
endmodule

register_file_tb.vcd
$date
   Mon Aug 25 01:09:42 2025
$end
$version
  2020.1
$end
$timescale
  1ps
$end
$scope module register_file_tb $end
$var reg 1 ! clk $end
$var reg 1 " we $end
$var reg 5 # rd [4:0] $end
$var reg 5 $ rs1 [4:0] $end
$var reg 5 % rs2 [4:0] $end
$var reg 32 & wd [31:0] $end
$var wire 32 ' rd1 [31:0] $end
$var wire 32 ( rd2 [31:0] $end
$var integer 32 ) i $end
$scope module uut $end
$var wire 1 * clk $end
$var wire 1 + we $end
$var wire 5 , rd [4:0] $end
$var wire 32 - wd [31:0] $end
$var wire 5 . rs1 [4:0] $end
$var wire 5 / rs2 [4:0] $end
$var wire 32 ' rd1 [31:0] $end
$var wire 32 ( rd2 [31:0] $end
$var integer 32 0 i $end
$upscope $end
$upscope $end
$enddefinitions $end
#0
$dumpvars
0!
0"
b0 #
b0 $
b0 %
b0 &
b0 '
b0 (
bx )
0*
0+
b0 ,
b0 -
b0 .
b0 /
b100000 0
$end
#5000
1!
1*
#10000
0!
0*
#15000
1!
1*
#20000
0!
1"
b1 #
b1 $
b0 %
b11011110101011011011111011101111 &
b0 '
0*
1+
b1 ,
b11011110101011011011111011101111 -
b1 .
#25000
1!
b11011110101011011011111011101111 '
b0 (
1*
#30000
0!
0"
0*
0+
#35000
1!
1*
#40000
0!
1"
b0 #
b0 $
b11001010111111101011101010111110 &
b0 '
0*
1+
b0 ,
b11001010111111101011101010111110 -
b0 .
#45000
1!
1*
#50000
0!
0"
0*
0+
#55000
1!
1*
#60000
0!
1"
b10 #
b10 $
b11 %
b10001000100010 &
b0 '
b0 (
0*
1+
b10 ,
b10001000100010 -
b10 .
b11 /
#65000
1!
b10001000100010 '
b0 (
1*
#70000
0!
0"
0*
0+
#75000
1!
1*
#80000
0!
1"
b11 #
b11 $
b10 %
b11001100110011 &
b0 '
b10001000100010 (
0*
1+
b11 ,
b11001100110011 -
b11 .
b10 /
#85000
1!
b11001100110011 '
b10001000100010 (
1*
#90000
0!
0"
0*
0+
#95000
1!
1*
#100000
0!
b100 )
0*
